sphinx_verilog_domain/__init__.py
sphinx_verilog_domain/verilog.lark
sphinx_verilog_domain/verilogdomain.py
sphinx_verilog_domain/version.py
sphinx_verilog_domain-0.2.post21.dist-info/LICENSE
sphinx_verilog_domain-0.2.post21.dist-info/METADATA
sphinx_verilog_domain-0.2.post21.dist-info/WHEEL
sphinx_verilog_domain-0.2.post21.dist-info/top_level.txt
sphinx_verilog_domain-0.2.post21.dist-info/RECORD
