Metadata-Version: 2.1
Name: sphinx-verilog-domain
Version: 0.2.post21
Summary: Verilog Domain for Sphinx
Home-page: https://github.com/SymbiFlow/sphinx-verilog-domain
Author: SymbiFlow Authors
Author-email: symbiflow@lists.librecores.org
License: UNKNOWN
Platform: UNKNOWN
Classifier: Development Status :: 4 - Beta
Classifier: Framework :: Sphinx :: Extension
Classifier: Intended Audience :: Developers
Classifier: License :: OSI Approved :: ISC License (ISCL)
Classifier: Programming Language :: Python :: 3
Classifier: Natural Language :: English
Classifier: Topic :: Documentation :: Sphinx
Classifier: Programming Language :: Python :: 3.7
Classifier: Topic :: Text Processing
Requires-Python: >=3.7
Requires-Dist: setuptools
Requires-Dist: docutils
Requires-Dist: sphinx
Requires-Dist: lark-parser
